pygff/GFF.py
pygff/__init__.py
pygff/_util.py
pygff/load.py
pygff/save.py
pygff-1.2.0.dist-info/LICENSE
pygff-1.2.0.dist-info/METADATA
pygff-1.2.0.dist-info/WHEEL
pygff-1.2.0.dist-info/top_level.txt
pygff-1.2.0.dist-info/RECORD
