Metadata-Version: 2.1
Name: pygff
Version: 1.2.0
Summary: A package to read and write Grace Format files (.gff/.segff)
Home-page: https://bitbucket.org/felixgremse/gff_file_format/src/master/
Author: Gremse-IT GmbH
Author-email: info@gremse-it.com
Maintainer: Nicholas Book
Maintainer-email: nbook@gremse-it.com
Classifier: Programming Language :: Python :: 3
Classifier: License :: OSI Approved :: MIT License
Classifier: Operating System :: OS Independent
Requires-Python: >=3.6
License-File: LICENSE
Requires-Dist: numpy >=1.13.3
Requires-Dist: pytest >=4.4.1
